godspeed/__init__.py
godspeed/_version.py
godspeed/godspeed.py
godspeed/cli/.gitkeep
godspeed/cli/godspeed.py
godspeed/data/.gitkeep
godspeed/data/emacs-logo/emacs-128x128.png
godspeed/data/emacs-logo/emacs.svg
godspeed/tests/__init__.py
godspeed/tests/test_godspeed.py
godspeed-0.0.0.dist-info/AUTHORS.rst
godspeed-0.0.0.dist-info/LICENSE
godspeed-0.0.0.dist-info/METADATA
godspeed-0.0.0.dist-info/WHEEL
godspeed-0.0.0.dist-info/entry_points.txt
godspeed-0.0.0.dist-info/top_level.txt
godspeed-0.0.0.dist-info/RECORD
